mLink/__init__.py
mLink/mLink.py
hc_mlink-1.6.0.dist-info/LICENSE
hc_mlink-1.6.0.dist-info/METADATA
hc_mlink-1.6.0.dist-info/WHEEL
hc_mlink-1.6.0.dist-info/top_level.txt
hc_mlink-1.6.0.dist-info/RECORD
