Metadata-Version: 2.1
Name: hc-mlink
Version: 1.6.0
Summary: mLink module for Hobby Components range of mLink I2C devices
Home-page: UNKNOWN
Author: HobbyComponents (Andrew Davies)
Author-email: <support@hobbycomponents.com.com>
License: UNKNOWN
Keywords: mLink,I2C,sensors,relay,interface,serial,infrared,motor,wireless,servo
Platform: UNKNOWN
Classifier: Development Status :: 4 - Beta
Classifier: Intended Audience :: Developers
Classifier: Programming Language :: Python
Classifier: Operating System :: Other OS
Requires-Dist: smbus2
